{
    "summary": {
        "_wandb": {
            "runtime": 5051
        },
        "iter_dt": 0.317724933,
        "val/loss": 3.060777425765991,
        "parameters": 123587328,
        "_step": 376,
        "_timestamp": 1721155575.0767112,
        "final-val/acc": 0.4377290904521942,
        "optimized_parameters": 123587328,
        "iter": 15000,
        "_runtime": 5051.2066032886505,
        "train/loss": 3.227799654006958,
        "final-val/perplexity": 22.09422440744449,
        "train/perplexity": 25.22403936399943,
        "lr": 0,
        "val/acc": 0.4431152045726776,
        "final-val/loss": 3.09531831741333,
        "val/perplexity": 21.34410025711268
    },
    "config": {
        "lr": 0.002,
        "moe": false,
        "opt": "adamw",
        "bias": false,
        "seed": 0,
        "beta1": 0.9,
        "beta2": 0.95,
        "dtype": "bfloat16",
        "model": "llama_norm",
        "wandb": true,
        "device": "cuda:0",
        "n_embd": 768,
        "n_head": 12,
        "compile": true,
        "dataset": "slimpajama",
        "dropout": 0,
        "n_layer": 12,
        "init_std": 0.02,
        "wa_dtype": "float32",
        "acc_steps": 2,
        "data_seed": 1337,
        "ema_decay": 0.95,
        "grad_clip": 1,
        "scale_emb": 10,
        "scheduler": "wsd",
        "tokenizer": "gpt2",
        "batch_size": 50,
        "decay_type": "linear",
        "from_dense": false,
        "iterations": 15000,
        "vocab_size": 50304,
        "wa_horizon": 500,
        "world_size": 2,
        "auto_resume": true,
        "data_in_ram": false,
        "moe_routing": "standard_gating",
        "multiple_of": 256,
        "resume_from": "/mloscratch/homes/haegele/improvegpt/exps/stable-124m_slimpajama_llama_norm_nlayers12_nhead12_lr0.002_sched_wsd_warmup300_decay_sqrt_0.0_iter50000_bs50x2_ws2_seed0_data_seed1337/ckpts/0",
        "rmsnorm_eps": 1e-05,
        "scale_depth": 1.4,
        "wa_interval": 5,
        "cos_final_lr": -1,
        "datasets_dir": "./datasets/",
        "ema_interval": 10,
        "eval_batches": 32,
        "full_eval_at": [],
        "log_dynamics": false,
        "log_interval": 50,
        "warmup_steps": 300,
        "weight_decay": 0.1,
        "config_format": "base",
        "cos_inf_steps": 0,
        "eval_interval": 200,
        "wandb_project": "re-slimpajama",
        "parallel_block": false,
        "use_pretrained": "none",
        "weight_average": false,
        "capacity_factor": 2,
        "eval_seq_prefix": "none",
        "experiment_name": null,
        "moe_num_experts": 8,
        "moe_router_loss": "load_balancing_z_loss",
        "resume_from_swa": null,
        "sequence_length": 512,
        "wa_use_temp_dir": false,
        "wsd_fract_decay": 0.4,
        "ema_after_warmup": false,
        "scale_base_model": 256,
        "wa_sweep_horizon": false,
        "wandb_run_prefix": "ann124-0.4",
        "max_num_wa_sweeps": 5,
        "moe_softmax_order": "topk_softmax",
        "moe_z_loss_factor": 0.01,
        "mlp_dim_exp_factor": 1,
        "plot_router_logits": false,
        "wsd_final_lr_scale": 0,
        "distributed_backend": "nccl",
        "dynamics_logger_cfg": "./src/logger/rotational_logger.yaml",
        "moe_aux_loss_factor": 0.1,
        "results_base_folder": "./exps",
        "latest_ckpt_interval": 1000,
        "moe_num_shared_experts": 0,
        "moe_entropy_loss_factor": 0.01,
        "moe_num_experts_per_tok": 2,
        "permanent_ckpt_interval": 0,
        "exponential_moving_average": false
    },
    "name": "ann124-0.4_slimpajama_llama_norm_nlayers12_nhead12_lr0.002_sched_wsd_warmup300_decay_linear_0.4_iter15000_bs50x2_ws2_seed0_data_seed1337",
    "history": {
        "final-val": {
            "iter": [
                15000
            ],
            "final_val_best_perplexity_wa": [],
            "final_val_best_loss_wa": [],
            "final_val_loss": [
                3.09531831741333
            ],
            "final_val_perplexity": [
                22.094224407444486
            ]
        },
        "val": {
            "iter": [
                0,
                200,
                400,
                600,
                800,
                1000,
                1200,
                1400,
                1600,
                1800,
                2000,
                2200,
                2400,
                2600,
                2800,
                3000,
                3200,
                3400,
                3600,
                3800,
                4000,
                4200,
                4400,
                4600,
                4800,
                5000,
                5200,
                5400,
                5600,
                5800,
                6000,
                6200,
                6400,
                6600,
                6800,
                7000,
                7200,
                7400,
                7600,
                7800,
                8000,
                8200,
                8400,
                8600,
                8800,
                9000,
                9200,
                9400,
                9600,
                9800,
                10000,
                10200,
                10400,
                10600,
                10800,
                11000,
                11200,
                11400,
                11600,
                11800,
                12000,
                12200,
                12400,
                12600,
                12800,
                13000,
                13200,
                13400,
                13600,
                13800,
                14000,
                14200,
                14400,
                14600,
                14800
            ],
            "val_perplexity": [
                54288.90243138202,
                212.82130308714528,
                98.26966671493602,
                66.6412139128968,
                55.95264842251831,
                49.930730532502196,
                45.833591608436166,
                42.86487312479246,
                40.69295801089723,
                39.07221612525113,
                37.68976279392894,
                36.63029308982827,
                35.573887196183335,
                34.795275878269486,
                34.07248193969023,
                33.539695113306415,
                32.98203862613935,
                32.54010781532511,
                32.10411380383007,
                31.70242895437402,
                31.26400016932238,
                30.945347980046893,
                30.619261541202913,
                30.33729832019558,
                30.039655772861007,
                29.77650841900781,
                29.65733783886903,
                29.46354644471042,
                29.33068059676622,
                29.087721563196766,
                28.91090423389047,
                28.73890947190481,
                28.600970523291995,
                28.462886089578944,
                28.385305011771187,
                28.257375600798813,
                28.01746840456135,
                27.927867788640015,
                27.859973638758493,
                27.70537879513658,
                27.692897264285207,
                27.49143220061824,
                27.45941264284167,
                27.366291667539443,
                27.33023425002159,
                27.18230511026162,
                26.967324439517785,
                26.771361294700363,
                26.614468020422922,
                26.342426479616144,
                26.069299363194006,
                25.887705444810962,
                25.697106136382466,
                25.481165309323522,
                25.239198884031865,
                24.998052023366107,
                24.812683566623743,
                24.610246969988072,
                24.395428973802456,
                24.25415407876094,
                23.969384536804146,
                23.820465693379614,
                23.565215403770917,
                23.36560179285889,
                23.17197680723987,
                22.96837150840911,
                22.765762759792704,
                22.569240212439873,
                22.34085347744393,
                22.16905694650666,
                21.978015501318744,
                21.786646414535152,
                21.61625627507375,
                21.471598439484943,
                21.344100257112682
            ],
            "val_loss": [
                10.902082443237305,
                5.360456466674805,
                4.587718486785889,
                4.199326038360596,
                4.024508476257324,
                3.9106392860412598,
                3.8250198364257812,
                3.7580552101135254,
                3.706057548522949,
                3.6654140949249268,
                3.6293909549713135,
                3.6008780002593994,
                3.5716142654418945,
                3.5494840145111084,
                3.5284924507141113,
                3.5127320289611816,
                3.4959654808044434,
                3.482475757598877,
                3.4689865112304688,
                3.4563956260681152,
                3.442469596862793,
                3.432224988937378,
                3.4216315746307373,
                3.4123802185058594,
                3.4025206565856934,
                3.3937220573425293,
                3.389711856842041,
                3.3831560611724854,
                3.378636360168457,
                3.3703184127807617,
                3.3642210960388184,
                3.3582541942596436,
                3.353442907333374,
                3.3486032485961914,
                3.3458738327026367,
                3.3413567543029785,
                3.3328304290771484,
                3.329627275466919,
                3.327193260192871,
                3.3216288089752197,
                3.3211781978607178,
                3.3138766288757324,
                3.312711238861084,
                3.309314250946045,
                3.3079957962036133,
                3.3025684356689453,
                3.294628143310547,
                3.28733491897583,
                3.2814571857452393,
                3.2711830139160156,
                3.260760545730591,
                3.253770351409912,
                3.246380567550659,
                3.2379417419433594,
                3.228400468826294,
                3.2188000679016113,
                3.2113571166992188,
                3.203165054321289,
                3.1943979263305664,
                3.1885900497436523,
                3.1767795085906982,
                3.1705472469329834,
                3.159773826599121,
                3.1512670516967773,
                3.1429457664489746,
                3.134120225906372,
                3.1252598762512207,
                3.1165900230407715,
                3.106419086456299,
                3.0986995697021484,
                3.0900447368621826,
                3.081299304962158,
                3.0734477043151855,
                3.0667331218719482,
                3.060777425765991
            ],
            "val_acc": [
                0.0011584472376853228,
                0.22345946729183197,
                0.2892480492591858,
                0.3311132788658142,
                0.3468383848667145,
                0.35752564668655396,
                0.36555540561676025,
                0.37141722440719604,
                0.3760083019733429,
                0.3799108862876892,
                0.38377806544303894,
                0.38590818643569946,
                0.38872313499450684,
                0.3907201886177063,
                0.3929187059402466,
                0.39400145411491394,
                0.3961181640625,
                0.3971789479255676,
                0.3992272913455963,
                0.4000537097454071,
                0.40166014432907104,
                0.4025952219963074,
                0.40363889932632446,
                0.40446043014526367,
                0.40519165992736816,
                0.40630125999450684,
                0.40666133165359497,
                0.40736082196235657,
                0.40751588344573975,
                0.4079638719558716,
                0.40904417634010315,
                0.40996092557907104,
                0.4102575480937958,
                0.410736083984375,
                0.41081786155700684,
                0.4113757312297821,
                0.41153931617736816,
                0.41248899698257446,
                0.41270506381988525,
                0.4132311940193176,
                0.4132006764411926,
                0.4137597680091858,
                0.4143103063106537,
                0.41455078125,
                0.41463378071784973,
                0.41560056805610657,
                0.4161364734172821,
                0.41688963770866394,
                0.41728758811950684,
                0.4189831614494324,
                0.41951659321784973,
                0.42033201456069946,
                0.4214111268520355,
                0.4223950207233429,
                0.4232556223869324,
                0.42454710602760315,
                0.42509031295776367,
                0.426361083984375,
                0.4271887242794037,
                0.4278320372104645,
                0.4288879334926605,
                0.4303564429283142,
                0.4313378930091858,
                0.4323071241378784,
                0.4331445097923279,
                0.4337707459926605,
                0.43504637479782104,
                0.4359753429889679,
                0.43719482421875,
                0.4383227229118347,
                0.4392175078392029,
                0.4403308033943176,
                0.44145143032073975,
                0.4423815608024597,
                0.4431152045726776
            ]
        },
        "train": {
            "iter": [
                50,
                100,
                150,
                200,
                250,
                300,
                350,
                400,
                450,
                500,
                550,
                600,
                650,
                700,
                750,
                800,
                850,
                900,
                950,
                1000,
                1050,
                1100,
                1150,
                1200,
                1250,
                1300,
                1350,
                1400,
                1450,
                1500,
                1550,
                1600,
                1650,
                1700,
                1750,
                1800,
                1850,
                1900,
                1950,
                2000,
                2050,
                2100,
                2150,
                2200,
                2250,
                2300,
                2350,
                2400,
                2450,
                2500,
                2550,
                2600,
                2650,
                2700,
                2750,
                2800,
                2850,
                2900,
                2950,
                3000,
                3050,
                3100,
                3150,
                3200,
                3250,
                3300,
                3350,
                3400,
                3450,
                3500,
                3550,
                3600,
                3650,
                3700,
                3750,
                3800,
                3850,
                3900,
                3950,
                4000,
                4050,
                4100,
                4150,
                4200,
                4250,
                4300,
                4350,
                4400,
                4450,
                4500,
                4550,
                4600,
                4650,
                4700,
                4750,
                4800,
                4850,
                4900,
                4950,
                5000,
                5050,
                5100,
                5150,
                5200,
                5250,
                5300,
                5350,
                5400,
                5450,
                5500,
                5550,
                5600,
                5650,
                5700,
                5750,
                5800,
                5850,
                5900,
                5950,
                6000,
                6050,
                6100,
                6150,
                6200,
                6250,
                6300,
                6350,
                6400,
                6450,
                6500,
                6550,
                6600,
                6650,
                6700,
                6750,
                6800,
                6850,
                6900,
                6950,
                7000,
                7050,
                7100,
                7150,
                7200,
                7250,
                7300,
                7350,
                7400,
                7450,
                7500,
                7550,
                7600,
                7650,
                7700,
                7750,
                7800,
                7850,
                7900,
                7950,
                8000,
                8050,
                8100,
                8150,
                8200,
                8250,
                8300,
                8350,
                8400,
                8450,
                8500,
                8550,
                8600,
                8650,
                8700,
                8750,
                8800,
                8850,
                8900,
                8950,
                9000,
                9050,
                9100,
                9150,
                9200,
                9250,
                9300,
                9350,
                9400,
                9450,
                9500,
                9550,
                9600,
                9650,
                9700,
                9750,
                9800,
                9850,
                9900,
                9950,
                10000,
                10050,
                10100,
                10150,
                10200,
                10250,
                10300,
                10350,
                10400,
                10450,
                10500,
                10550,
                10600,
                10650,
                10700,
                10750,
                10800,
                10850,
                10900,
                10950,
                11000,
                11050,
                11100,
                11150,
                11200,
                11250,
                11300,
                11350,
                11400,
                11450,
                11500,
                11550,
                11600,
                11650,
                11700,
                11750,
                11800,
                11850,
                11900,
                11950,
                12000,
                12050,
                12100,
                12150,
                12200,
                12250,
                12300,
                12350,
                12400,
                12450,
                12500,
                12550,
                12600,
                12650,
                12700,
                12750,
                12800,
                12850,
                12900,
                12950,
                13000,
                13050,
                13100,
                13150,
                13200,
                13250,
                13300,
                13350,
                13400,
                13450,
                13500,
                13550,
                13600,
                13650,
                13700,
                13750,
                13800,
                13850,
                13900,
                13950,
                14000,
                14050,
                14100,
                14150,
                14200,
                14250,
                14300,
                14350,
                14400,
                14450,
                14500,
                14550,
                14600,
                14650,
                14700,
                14750,
                14800,
                14850,
                14900,
                14950,
                15000
            ],
            "train_perplexity": [
                963.106105372013,
                438.9778750134917,
                306.6748542570414,
                198.66377721522983,
                214.83922094045175,
                154.03537451350078,
                165.06083210235556,
                107.5685623527943,
                106.42967960959007,
                91.64323425239454,
                82.16096693729817,
                75.40812519461812,
                82.21849945866495,
                60.800175819762295,
                63.669076422338456,
                59.44702056186497,
                69.27280316515409,
                52.127934840162915,
                46.919194344076864,
                54.14960369150179,
                53.77118964825917,
                42.54864975664352,
                53.22988852132532,
                43.71644501995072,
                55.70026358258111,
                48.15428701717456,
                53.10682690274871,
                49.13027595637162,
                39.34671728284506,
                51.63007763909289,
                52.196882669769444,
                45.00265602918841,
                38.4674026016483,
                48.72149594903305,
                36.53114694046886,
                42.982746268188144,
                47.3575211187248,
                41.35919173449747,
                41.7505826729761,
                40.15504990419673,
                48.14341586156723,
                48.317004131372215,
                38.339473872129915,
                43.483482458011,
                38.71923367200348,
                30.741293241485867,
                42.01714497628844,
                41.557760358258534,
                48.667139703269235,
                38.95529512684426,
                41.83074032070903,
                36.45983195349458,
                40.801307858728514,
                35.16143426314575,
                49.11084699852462,
                34.07437476945753,
                40.382694835915196,
                36.43202593644924,
                38.57562040517699,
                35.36879654546711,
                41.309099682134025,
                37.652274163542,
                42.27147867882515,
                41.09007273709021,
                38.758181971229604,
                36.63214460396988,
                40.796317811063936,
                30.09537049645512,
                45.723835564607356,
                35.20371065145086,
                27.789547817572412,
                34.04466216723709,
                33.748032107818396,
                31.140301854057004,
                39.513064408459414,
                26.89255667223456,
                35.893385497034316,
                37.47107106084879,
                28.932997497453506,
                41.7585168507742,
                34.3702674631939,
                30.67956937153707,
                35.241987710714156,
                39.45954433576271,
                27.396778649400236,
                33.705647476287865,
                37.793522157232516,
                29.78702429144941,
                27.223768214207436,
                36.30799206703729,
                40.64002951339644,
                36.776667288376025,
                34.57257647962597,
                36.490965088083875,
                32.07427625094668,
                39.40629405391792,
                35.08342365790853,
                32.06579674008076,
                30.83230356850778,
                32.57380342648463,
                32.708194313280444,
                38.139492994922264,
                37.04201733591319,
                26.090664231397902,
                32.4865972755573,
                32.35139680061464,
                41.260435653389386,
                33.3876677628425,
                28.91965263729015,
                35.48623758332251,
                29.153283001263667,
                39.47178588891724,
                28.13970220892895,
                31.638020951515017,
                31.073894492095512,
                36.280803547590324,
                30.98900451034192,
                35.736235640277,
                44.222860644571504,
                26.701427256287566,
                30.008209545931383,
                31.30776288025332,
                29.70392182864625,
                27.843591826709922,
                34.17922922338417,
                30.021312313261156,
                31.29812789075558,
                43.32038031347002,
                31.84141504195266,
                37.20180487097758,
                27.953148299892884,
                34.673102421238674,
                33.8680845295732,
                42.15753609704593,
                40.47821125614027,
                26.403468380043623,
                36.8320013634518,
                29.97830429688842,
                30.401232726273527,
                34.125439578509145,
                24.875867724760564,
                37.03927084148704,
                35.23112516082173,
                31.86321033203023,
                25.819993570929523,
                41.702790513503786,
                37.487521784781535,
                28.371211643450795,
                27.023151688569865,
                32.46518829330528,
                31.077095167278916,
                30.81382871932122,
                32.99081548819235,
                32.72937337786094,
                28.88090815357744,
                28.06774616421815,
                32.327078610443465,
                34.29166564843246,
                31.745677604576706,
                24.02187469150635,
                34.09173196422646,
                31.880429277853263,
                31.514443156739148,
                33.570959924404754,
                34.730073713979415,
                29.929120681966015,
                34.492196204648415,
                26.553723331739526,
                27.904279967302134,
                31.337940842899854,
                26.207290919298142,
                24.417366356288383,
                33.022072520968855,
                23.54591293664779,
                34.19615064708545,
                36.57460803817344,
                31.90219803043539,
                31.72175422242061,
                30.414920434412235,
                32.41500805519833,
                29.950199686587922,
                33.4091991778828,
                37.04501133513354,
                27.316052530762697,
                30.009583243267375,
                32.95261857938837,
                33.53572109766592,
                29.504810020636125,
                35.06594613586718,
                37.64161997733719,
                28.278490753862176,
                28.250120698407002,
                33.90473152235964,
                30.805315204407346,
                31.588223008105206,
                27.88414892132593,
                32.002451126932634,
                29.891967006750804,
                31.966564606312563,
                32.95448062515335,
                39.340760810104484,
                26.51981139830712,
                34.259280394976656,
                26.3787654858759,
                37.495495074962285,
                28.19418519091461,
                27.958087164303173,
                28.402567586593996,
                27.001139110139402,
                29.179387532941533,
                29.190430227673623,
                28.859811068399893,
                27.407427710025424,
                22.737366071298574,
                25.104024219844355,
                32.144338904652564,
                26.546064051550278,
                32.69039578495755,
                31.18737110172229,
                31.796474267510053,
                30.668548287928154,
                26.296185962191878,
                25.35420159364313,
                28.931224724771393,
                30.783935284213204,
                29.36763375378831,
                27.868151548069275,
                25.74776223923225,
                37.84696616106426,
                27.99913145589788,
                31.590324286747865,
                32.49490140889545,
                32.26894030155534,
                28.505303497456268,
                28.398078307464726,
                21.210369311621122,
                30.563895870434774,
                31.752611340581314,
                28.206872483305254,
                24.124289571475252,
                20.920247371671763,
                18.260626803340987,
                24.717279940388895,
                25.56328188424034,
                23.635076577769947,
                26.560757889630242,
                21.09163716238091,
                19.001837005003633,
                27.255779422595175,
                25.28344209770119,
                31.643339274751145,
                32.21034593964318,
                31.986592342118364,
                23.758874614112276,
                26.09384931918988,
                24.82917046256774,
                19.890716314397466,
                24.080834590032882,
                33.97929487625124,
                22.595702948678767,
                22.864882870970078,
                23.081192145877463,
                21.960777544410107,
                26.913999465443194,
                29.235730164854676,
                22.26385915812047,
                24.5429914564303,
                23.631960607403556,
                25.07593315911907,
                28.617102001471917,
                26.90930278267485,
                26.115228080745176,
                29.816930666454006,
                27.2364019453273,
                20.13652299954159,
                24.027230274069897,
                33.44322861995791,
                28.607960850521795,
                28.998327732902116,
                24.347015501550953,
                26.406257244738878,
                22.731788539437762,
                28.149082986769905,
                22.92054398172248,
                21.417847423226394,
                24.733414495111912,
                25.07986736303904,
                18.075982785744653,
                25.597990689527183,
                22.044206637668797,
                20.373774077629893,
                22.835692868671003,
                24.424923897372544,
                23.46148745670332,
                27.086746134534316,
                24.917905591071484,
                24.914287853141584,
                21.172566993043638,
                24.44299461594141,
                25.224039363999434
            ],
            "train_lr": [
                0.00035,
                0.0006799999999999999,
                0.00101,
                0.0013399999999999998,
                0.0016700000000000003,
                0.002,
                0.002,
                0.002,
                0.002,
                0.002,
                0.002,
                0.002,
                0.002,
                0.002,
                0.002,
                0.002,
                0.002,
                0.002,
                0.002,
                0.002,
                0.002,
                0.002,
                0.002,
                0.002,
                0.002,
                0.002,
                0.002,
                0.002,
                0.002,
                0.002,
                0.002,
                0.002,
                0.002,
                0.002,
                0.002,
                0.002,
                0.002,
                0.002,
                0.002,
                0.002,
                0.002,
                0.002,
                0.002,
                0.002,
                0.002,
                0.002,
                0.002,
                0.002,
                0.002,
                0.002,
                0.002,
                0.002,
                0.002,
                0.002,
                0.002,
                0.002,
                0.002,
                0.002,
                0.002,
                0.002,
                0.002,
                0.002,
                0.002,
                0.002,
                0.002,
                0.002,
                0.002,
                0.002,
                0.002,
                0.002,
                0.002,
                0.002,
                0.002,
                0.002,
                0.002,
                0.002,
                0.002,
                0.002,
                0.002,
                0.002,
                0.002,
                0.002,
                0.002,
                0.002,
                0.002,
                0.002,
                0.002,
                0.002,
                0.002,
                0.002,
                0.002,
                0.002,
                0.002,
                0.002,
                0.002,
                0.002,
                0.002,
                0.002,
                0.002,
                0.002,
                0.002,
                0.002,
                0.002,
                0.002,
                0.002,
                0.002,
                0.002,
                0.002,
                0.002,
                0.002,
                0.002,
                0.002,
                0.002,
                0.002,
                0.002,
                0.002,
                0.002,
                0.002,
                0.002,
                0.002,
                0.002,
                0.002,
                0.002,
                0.002,
                0.002,
                0.002,
                0.002,
                0.002,
                0.002,
                0.002,
                0.002,
                0.002,
                0.002,
                0.002,
                0.002,
                0.002,
                0.002,
                0.002,
                0.002,
                0.002,
                0.002,
                0.002,
                0.002,
                0.002,
                0.002,
                0.002,
                0.002,
                0.002,
                0.002,
                0.002,
                0.002,
                0.002,
                0.002,
                0.002,
                0.002,
                0.002,
                0.002,
                0.002,
                0.002,
                0.002,
                0.002,
                0.002,
                0.002,
                0.002,
                0.002,
                0.002,
                0.002,
                0.002,
                0.002,
                0.002,
                0.002,
                0.002,
                0.002,
                0.002,
                0.002,
                0.002,
                0.002,
                0.002,
                0.002,
                0.002,
                0.0019833333333333335,
                0.0019666666666666665,
                0.00195,
                0.0019333333333333333,
                0.0019166666666666668,
                0.0019,
                0.0018833333333333334,
                0.0018666666666666666,
                0.00185,
                0.0018333333333333333,
                0.0018166666666666667,
                0.0018000000000000002,
                0.0017833333333333332,
                0.0017666666666666666,
                0.00175,
                0.0017333333333333335,
                0.001716666666666667,
                0.0017,
                0.0016833333333333333,
                0.0016666666666666668,
                0.00165,
                0.0016333333333333334,
                0.0016166666666666666,
                0.0016,
                0.0015833333333333333,
                0.0015666666666666667,
                0.0015500000000000002,
                0.0015333333333333332,
                0.0015166666666666666,
                0.0015,
                0.0014833333333333335,
                0.001466666666666667,
                0.00145,
                0.0014333333333333333,
                0.0014166666666666666,
                0.0014,
                0.0013833333333333334,
                0.0013666666666666666,
                0.00135,
                0.0013333333333333335,
                0.0013166666666666667,
                0.0013000000000000002,
                0.0012833333333333332,
                0.0012666666666666666,
                0.00125,
                0.0012333333333333335,
                0.001216666666666667,
                0.0012,
                0.0011833333333333333,
                0.0011666666666666665,
                0.00115,
                0.0011333333333333334,
                0.0011166666666666666,
                0.0011,
                0.0010833333333333335,
                0.0010666666666666667,
                0.0010500000000000002,
                0.0010333333333333332,
                0.0010166666666666666,
                0.001,
                0.0009833333333333335,
                0.0009666666666666666,
                0.00095,
                0.0009333333333333333,
                0.0009166666666666668,
                0.0009,
                0.0008833333333333333,
                0.0008666666666666667,
                0.0008500000000000001,
                0.0008333333333333333,
                0.0008166666666666667,
                0.0008,
                0.0007833333333333335,
                0.0007666666666666666,
                0.00075,
                0.0007333333333333334,
                0.0007166666666666666,
                0.0007,
                0.0006833333333333333,
                0.0006666666666666668,
                0.00065,
                0.0006333333333333333,
                0.0006166666666666667,
                0.0006000000000000001,
                0.0005833333333333333,
                0.0005666666666666667,
                0.00055,
                0.0005333333333333335,
                0.0005166666666666666,
                0.0005,
                0.0004833333333333334,
                0.00046666666666666655,
                0.00045,
                0.00043333333333333337,
                0.00041666666666666675,
                0.0003999999999999999,
                0.0003833333333333333,
                0.0003666666666666667,
                0.0003500000000000001,
                0.00033333333333333327,
                0.00031666666666666665,
                0.00030000000000000003,
                0.00028333333333333346,
                0.0002666666666666666,
                0.00025,
                0.00023333333333333339,
                0.00021666666666666658,
                0.00019999999999999996,
                0.00018333333333333336,
                0.00016666666666666674,
                0.0001499999999999999,
                0.0001333333333333333,
                0.00011666666666666669,
                0.00010000000000000009,
                8.333333333333326e-05,
                6.666666666666666e-05,
                5.000000000000004e-05,
                3.3333333333333437e-05,
                1.6666666666666606e-05,
                0
            ],
            "train_loss": [
                6.870168209075928,
                6.084453105926514,
                5.725791931152344,
                5.291617393493652,
                5.369893550872803,
                5.0371856689453125,
                5.106317520141602,
                4.678131580352783,
                4.667487621307373,
                4.517906188964844,
                4.4086833000183105,
                4.322917938232422,
                4.409383296966553,
                4.107595443725586,
                4.1537017822265625,
                4.08508825302124,
                4.238055229187012,
                3.9537036418914795,
                3.8484294414520264,
                3.991753339767456,
                3.9847404956817627,
                3.750650644302368,
                3.9746227264404297,
                3.777726888656616,
                4.0199875831604,
                3.874412775039673,
                3.9723081588745117,
                3.8944780826568604,
                3.672415018081665,
                3.9441070556640625,
                3.9550254344940186,
                3.8067240715026855,
                3.649813652038574,
                3.886122941970825,
                3.598167657852173,
                3.760801315307617,
                3.8577282428741455,
                3.722297191619873,
                3.7317159175872803,
                3.6927506923675537,
                3.8741869926452637,
                3.877786159515381,
                3.646482467651367,
                3.772383689880371,
                3.656338930130005,
                3.4256091117858887,
                3.7380802631378174,
                3.7270867824554443,
                3.8850066661834717,
                3.66241717338562,
                3.7336339950561523,
                3.5962135791778564,
                3.708716630935669,
                3.5599522590637207,
                3.894082546234131,
                3.528548002243042,
                3.698403835296631,
                3.5954506397247314,
                3.652622938156128,
                3.5658323764801025,
                3.7210853099823,
                3.6283957958221436,
                3.744115114212036,
                3.715769052505493,
                3.657344341278076,
                3.600928544998169,
                3.70859432220459,
                3.4043736457824707,
                3.822622299194336,
                3.5611538887023926,
                3.324662208557129,
                3.5276756286621094,
                3.5189244747161865,
                3.438505172729492,
                3.676633834838867,
                3.291851758956909,
                3.5805554389953613,
                3.6235716342926025,
                3.3649849891662598,
                3.731905937194824,
                3.53719425201416,
                3.4235992431640625,
                3.5622406005859375,
                3.675278425216675,
                3.310427665710449,
                3.517667770385742,
                3.6321401596069336,
                3.3940751552581787,
                3.3040926456451416,
                3.5920403003692627,
                3.704756021499634,
                3.6048660278320312,
                3.543063163757324,
                3.59706711769104,
                3.4680566787719727,
                3.6739280223846436,
                3.5577311515808105,
                3.467792272567749,
                3.428565263748169,
                3.483510732650757,
                3.4876279830932617,
                3.6412527561187744,
                3.6120553016662598,
                3.261579751968384,
                3.480829954147339,
                3.4766595363616943,
                3.7199065685272217,
                3.5081889629364014,
                3.3645236492156982,
                3.5691473484039307,
                3.3725697994232178,
                3.675588607788086,
                3.337183713912964,
                3.454361915588379,
                3.436370372772217,
                3.5912911891937256,
                3.4336347579956055,
                3.576167583465576,
                3.7892444133758545,
                3.284719228744507,
                3.4014732837677,
                3.443868398666382,
                3.3912813663482666,
                3.3266050815582275,
                3.531620502471924,
                3.401909828186035,
                3.4435606002807617,
                3.7686257362365723,
                3.4607701301574707,
                3.6163597106933594,
                3.3305320739746094,
                3.545966625213623,
                3.522475481033325,
                3.7414159774780273,
                3.7007663249969482,
                3.2734975814819336,
                3.6063694953918457,
                3.4004762172698975,
                3.414485454559326,
                3.530045509338379,
                3.213900327682495,
                3.611981153488159,
                3.561932325363159,
                3.461454391479492,
                3.2511513233184814,
                3.7305705547332764,
                3.6240105628967285,
                3.345377206802368,
                3.296696186065674,
                3.480170726776123,
                3.4364733695983887,
                3.4279658794403076,
                3.4962315559387207,
                3.4882752895355225,
                3.36318302154541,
                3.334623336791992,
                3.475907564163208,
                3.534904718399048,
                3.457758903503418,
                3.178966999053955,
                3.529057264328003,
                3.4619946479797363,
                3.4504482746124268,
                3.5136637687683105,
                3.5476083755493164,
                3.398834228515625,
                3.5407354831695557,
                3.27917218208313,
                3.328782320022583,
                3.4448318481445312,
                3.2660398483276367,
                3.1952967643737793,
                3.497178554534912,
                3.158954381942749,
                3.5321154594421387,
                3.5993566513061523,
                3.462677240371704,
                3.457005023956299,
                3.41493558883667,
                3.478623867034912,
                3.399538278579712,
                3.508833646774292,
                3.612136125564575,
                3.307476758956909,
                3.4015190601348877,
                3.495073080062866,
                3.512613534927368,
                3.3845555782318115,
                3.5572328567504883,
                3.62811279296875,
                3.3421037197113037,
                3.341099977493286,
                3.52355694770813,
                3.427689552307129,
                3.452786684036255,
                3.3280606269836426,
                3.4658148288726807,
                3.397592067718506,
                3.4646928310394287,
                3.4951295852661133,
                3.6722636222839355,
                3.2778942584991455,
                3.5339598655700684,
                3.272561550140381,
                3.624223232269287,
                3.339118003845215,
                3.3307087421417236,
                3.3464818000793457,
                3.2958812713623047,
                3.373464822769165,
                3.373843193054199,
                3.362452268600464,
                3.3108162879943848,
                3.124011754989624,
                3.2230303287506104,
                3.47023868560791,
                3.278883695602417,
                3.487083673477173,
                3.4400155544281006,
                3.459357738494873,
                3.4232399463653564,
                3.269426107406616,
                3.2329466342926025,
                3.3649237155914307,
                3.426995277404785,
                3.3798954486846924,
                3.327486753463745,
                3.248349905014038,
                3.6335532665252686,
                3.3321757316589355,
                3.452853202819824,
                3.4810855388641357,
                3.474107503890991,
                3.3500924110412598,
                3.3463237285614014,
                3.054492235183716,
                3.4198217391967773,
                3.457977294921875,
                3.3395678997039795,
                3.1832213401794434,
                3.040719509124756,
                2.9047491550445557,
                3.2075047492980957,
                3.241159200668335,
                3.162734031677246,
                3.2794370651245117,
                3.0488786697387695,
                2.94453763961792,
                3.305267810821533,
                3.230151891708374,
                3.4545300006866455,
                3.4722900390625,
                3.4653191566467285,
                3.1679582595825195,
                3.261701822280884,
                3.2120213508605957,
                2.990255117416382,
                3.1814184188842773,
                3.5257537364959717,
                3.1177618503570557,
                3.1296043395996094,
                3.1390202045440674,
                3.0892601013183594,
                3.2926487922668457,
                3.375393867492676,
                3.102966785430908,
                3.2004284858703613,
                3.162602186203003,
                3.2219107151031494,
                3.354006767272949,
                3.2924742698669434,
                3.2625207901000977,
                3.395078659057617,
                3.3045566082000732,
                3.002537250518799,
                3.179189920425415,
                3.5098516941070557,
                3.353687286376953,
                3.3672404289245605,
                3.192411422729492,
                3.2736032009124756,
                3.1237664222717285,
                3.337517023086548,
                3.132035732269287,
                3.0642266273498535,
                3.2081573009490967,
                3.2220675945281982,
                2.8945860862731934,
                3.242516040802002,
                3.0930519104003906,
                3.0142505168914795,
                3.128326892852783,
                3.195606231689453,
                3.155362367630005,
                3.299046754837036,
                3.2155888080596924,
                3.2154436111450195,
                3.052708387374878,
                3.196345806121826,
                3.227799654006958
            ]
        },
        "wa": {
            "iter": [],
            "val_perplexity_wa": [],
            "val_loss_wa": [],
            "val_acc_wa": [],
            "val_best_perplexity_wa": []
        },
        "ema": {
            "iter": [],
            "val_perplexity_ema": [],
            "val_acc_ema": [],
            "val_loss_ema": []
        }
    }
}